comandos/__init__.py
comandos/_modidx.py
comandos/core.py
comandos/dotplot_util.py
comandos/genes.py
comandos/plot.py
comandos/report.py
comandos/util.py
comandos-0.0.1.dist-info/LICENSE
comandos-0.0.1.dist-info/METADATA
comandos-0.0.1.dist-info/WHEEL
comandos-0.0.1.dist-info/entry_points.txt
comandos-0.0.1.dist-info/top_level.txt
comandos-0.0.1.dist-info/RECORD
