Metadata-Version: 2.1
Name: comandos
Version: 0.0.1
Summary: Advanced visualizations for the comparison of single-cell datasets. Conceived as a SAMap add-on, but many parts do not require it.
Home-page: https://github.com/galicae/comandos
Author: Niko Papadopoulos
Author-email: nikolaos.papadopoulos@univie.ac.at
License: Apache Software License 2.0
Keywords: nbdev jupyter notebook python
Classifier: Development Status :: 4 - Beta
Classifier: Intended Audience :: Developers
Classifier: Natural Language :: English
Classifier: Programming Language :: Python :: 3.7
Classifier: Programming Language :: Python :: 3.8
Classifier: Programming Language :: Python :: 3.9
Classifier: Programming Language :: Python :: 3.10
Classifier: License :: OSI Approved :: Apache Software License
Requires-Python: >=3.7
License-File: LICENSE
Requires-Dist: fastcore
Requires-Dist: jupyterlab
Requires-Dist: black
Requires-Dist: scanpy
Requires-Dist: seaborn
Requires-Dist: plotly
Requires-Dist: sam-algorithm
Requires-Dist: samap
Provides-Extra: dev
